{
  "nodes": [
    {
      "id": "npr.org",
      "size": 11995,
      "name": "NPR News",
      "favicon": "https://media.npr.org/templates/favicon/favicon-32x32.png",
      "avg_tone": -2.547762368559911
    },
    {
      "id": "kdvr.com",
      "size": 5589,
      "name": "FOX31 Denver KDVR",
      "favicon": "https://secure.gravatar.com/blavatar/17e52d5bd05a36821dc7d1d5f90e105c?s=32",
      "avg_tone": -3.227018774089482
    },
    {
      "id": "ktla.com",
      "size": 7975,
      "name": "KTLA ",
      "favicon": "https://secure.gravatar.com/blavatar/77bb48cc2507c6a01607fe346372a8be?s=32",
      "avg_tone": -3.685475039263877
    },
    {
      "id": "kxan.com",
      "size": 5189,
      "name": "KXAN News ",
      "favicon": "https://www.kxan.com/nxs-main-v2-theme/images/color_schemes/kxan/favicon.ico",
      "avg_tone": -3.1274959557690782
    },
    {
      "id": "wtop.com",
      "size": 25626,
      "name": "WTOP",
      "favicon": "https://wtop.com/wp-content/themes/wtop/assets/img/favicons/favicon-192x192.png",
      "avg_tone": -3.7423973397790204
    },
    {
      "id": "abc13.com",
      "size": 15733,
      "name": " ABC13 Houston ",
      "favicon": "https://cdns.abclocal.go.com/assets/news/ktrk/images/logos/favicon.ico",
      "avg_tone": -3.33438229306773
    },
    {
      "id": "kron4.com",
      "size": 7085,
      "name": "KRON4.com ",
      "favicon": "https://www.kron4.com/nxs-main-v2-theme/images/color_schemes/kron/favicon.ico",
      "avg_tone": -3.7783548516584573
    },
    {
      "id": "wgntv.com",
      "size": 5951,
      "name": "WGN",
      "favicon": "https://tribwgntv.files.wordpress.com/2017/05/cropped-box9_512_512.png?w=16",
      "avg_tone": -3.5461847585463118
    },
    {
      "id": "boston.com",
      "size": 7464,
      "name": "Boston.com ",
      "favicon": "https://www.boston.com/wp-content/themes/bdc/images/favicons/favicon.ico",
      "avg_tone": -2.6929069326410895
    },
    {
      "id": "nypost.com",
      "size": 21680,
      "name": "New York Post",
      "favicon": "https://s2.wp.com/wp-content/themes/vip/nypost-2016/static/images/favicon-nypost/favicon.ico",
      "avg_tone": -3.8591962241698017
    },
    {
      "id": "philly.com",
      "size": 18865,
      "name": "Philly.com News ",
      "favicon": "http://philly.com/pb/resources/images/pmn/favicon.ico",
      "avg_tone": -2.803576510039338
    },
    {
      "id": "cbsnews.com",
      "size": 16032,
      "name": "CBS News",
      "favicon": null,
      "avg_tone": -3.186826844054065
    },
    {
      "id": "fox2now.com",
      "size": 8832,
      "name": "FOX2now",
      "favicon": "https://secure.gravatar.com/blavatar/755e6b237618f1b2fe250cb518a56c05?s=32",
      "avg_tone": -3.610640181809315
    },
    {
      "id": "foxnews.com",
      "size": 52521,
      "name": "Fox News ",
      "favicon": "http://foxnews.com//static.foxnews.com/static/orion/styles/img/fox-news/favicons/favicon.ico",
      "avg_tone": -3.8580666550189138
    },
    {
      "id": "latimes.com",
      "size": 26274,
      "name": "Los Angeles Times ",
      "favicon": "http://latimes.com/pb/resources/images/lat_icons/favicon.ico?v=16",
      "avg_tone": -2.546748105145341
    },
    {
      "id": "nbcnews.com",
      "size": 51525,
      "name": "NBC News",
      "favicon": "https://nodeassets.nbcnews.com/cdnassets/projects/ramen/favicon/nbcnews/all-other-sizes-PNG.ico/favicon.ico",
      "avg_tone": -2.8459838131210833
    },
    {
      "id": "newsday.com",
      "size": 12234,
      "name": "Newsday",
      "favicon": "http://newsday.com/img/newsday/favicon.ico",
      "avg_tone": -2.552689128786676
    },
    {
      "id": "newsmax.com",
      "size": 26146,
      "name": "Newsmax ",
      "favicon": "http://newsmax.com/App_Themes/Newsmax/images/favicon.ico",
      "avg_tone": -2.5577917131635393
    },
    {
      "id": "nytimes.com",
      "size": 33483,
      "name": "The New York Times",
      "favicon": "http://nytimes.com/vi-assets/static-assets/favicon-4bf96cb6a1093748bf5b3c429accb9b4.ico",
      "avg_tone": -2.6328815523118365
    },
    {
      "id": "abc7news.com",
      "size": 12630,
      "name": "ABC7 News",
      "favicon": "https://cdns.abclocal.go.com/assets/news/kgo/images/logos/favicon.ico",
      "avg_tone": -2.9487595806374314
    },
    {
      "id": "autonews.com",
      "size": 2780,
      "name": "Automotive News",
      "favicon": "https://crain-platform-autonews-prod.s3.amazonaws.com/s3fs-public/AN-AppIcon.jpg",
      "avg_tone": -1.1123622361341745
    },
    {
      "id": "laweekly.com",
      "size": 424,
      "name": "L.A. Weekly ",
      "favicon": "http://laweekly.com/theme/law/apple-touch-icon.png",
      "avg_tone": -0.007817185861961994
    },
    {
      "id": "newsweek.com",
      "size": 21590,
      "name": "Newsweek",
      "favicon": "https://s.newsweek.com/sites/www.newsweek.com/themes/newsweek/favicon.ico",
      "avg_tone": -2.9222383572331707
    },
    {
      "id": "observer.com",
      "size": 2348,
      "name": "Observer",
      "favicon": "http://observer.com//s2.wp.com/wp-content/themes/vip/newyorkobserver-2014/images/favicons/favicon-32x32.png",
      "avg_tone": -1.5556826013049958
    },
    {
      "id": "politico.com",
      "size": 11487,
      "name": "POLITICO",
      "favicon": "https://static.politico.com/cf/05/ee684a274496b04fa20ba2978da1/politico.png",
      "avg_tone": -1.6965296141042316
    },
    {
      "id": "stltoday.com",
      "size": 42411,
      "name": "STLtoday",
      "favicon": "https://www.stltoday.com/content/tncms/site/icon.ico",
      "avg_tone": -3.1752377306355872
    },
    {
      "id": "theonion.com",
      "size": 563,
      "name": "The Onion",
      "favicon": "https://i.kinja-img.com/gawker-media/image/upload/s--4Aggfcp6--/c_fill,fl_progressive,g_center,h_80,q_80,w_80/eti2h1r4wg0bqxctxenl.png",
      "avg_tone": -2.317611537009688
    },
    {
      "id": "usatoday.com",
      "size": 20497,
      "name": "USA TODAY",
      "favicon": "https://www.gannett-cdn.com/gannett-web/properties/usatoday/logos-and-branding/logo-icon.png",
      "avg_tone": -2.40369359182964
    },
    {
      "id": "westword.com",
      "size": 1417,
      "name": "Westword",
      "favicon": "http://westword.com/theme/den/apple-touch-icon.png",
      "avg_tone": -0.46456569097934064
    },
    {
      "id": "breitbart.com",
      "size": 19884,
      "name": "Breitbart News Network",
      "favicon": "http://breitbart.com/t/assets/icons/w-logo-orange.png",
      "avg_tone": -3.1893337149796546
    },
    {
      "id": "gothamist.com",
      "size": 1052,
      "name": "Gothamist",
      "favicon": null,
      "avg_tone": -2.559136773758485
    },
    {
      "id": "seattlepi.com",
      "size": 37154,
      "name": "Seattlepi",
      "favicon": null,
      "avg_tone": -3.3657682120792685
    },
    {
      "id": "denverpost.com",
      "size": 6133,
      "name": "The Denver Post",
      "favicon": "https://www.denverpost.com/wp-content/uploads/2016/05/cropped-DP_bug_denverpost.jpg?w=32",
      "avg_tone": -2.7795060515981698
    },
    {
      "id": "nbcchicago.com",
      "size": 2347,
      "name": "NBC Chicago",
      "favicon": "https://media.nbcchicago.com/designimages/favicon-chi.ico",
      "avg_tone": -3.495048832873037
    },
    {
      "id": "nbcnewyork.com",
      "size": 2983,
      "name": "NBC New York",
      "favicon": "https://media.nbcnewyork.com/designimages/favicon-ny.ico",
      "avg_tone": -3.7353274030875117
    },
    {
      "id": "twincities.com",
      "size": 2914,
      "name": "Pioneer Press",
      "favicon": "https://www.twincities.com/wp-content/uploads/2017/06/cropped-faviconwhite-copy.jpg?w=32",
      "avg_tone": -2.739504853045664
    },
    {
      "id": "mercurynews.com",
      "size": 7721,
      "name": "The Mercury News",
      "favicon": "https://www.mercurynews.com/wp-content/uploads/2016/10/32x32-mercury-news-white.png?w=32",
      "avg_tone": -2.8486923096212915
    },
    {
      "id": "miamiherald.com",
      "size": 48835,
      "name": "Miami Herald ",
      "favicon": "https://www.miamiherald.com/wps/source/images/miamiherald/favicon.png",
      "avg_tone": -3.046693352230571
    },
    {
      "id": "nbcsandiego.com",
      "size": 2006,
      "name": "NBC 7 San Diego ",
      "favicon": "https://media.nbcsandiego.com/designimages/favicon-dgo.ico",
      "avg_tone": -3.4097252562813236
    },
    {
      "id": "nydailynews.com",
      "size": 36094,
      "name": "New York Daily News ",
      "favicon": "http://nydailynews.com/pb/resources/images/nydn_icons/favicon.ico?v=106",
      "avg_tone": -3.7023314650740207
    },
    {
      "id": "phillyvoice.com",
      "size": 2244,
      "name": "PhillyVoice",
      "favicon": "http://phillyvoice.com/static/global/images/favicon.ico",
      "avg_tone": -2.5098156117797403
    },
    {
      "id": "bostonherald.com",
      "size": 17704,
      "name": "Boston Herald",
      "favicon": null,
      "avg_tone": -3.434781514220698
    },
    {
      "id": "seattletimes.com",
      "size": 79974,
      "name": "The Seattle Times",
      "favicon": null,
      "avg_tone": -3.9792873504006416
    },
    {
      "id": "villagevoice.com",
      "size": 626,
      "name": "Village Voice",
      "favicon": "https://villagevoice.freetls.fastly.net/wp-content/uploads/2017/05/cropped-vv_ico_512x512-32x32.png",
      "avg_tone": -1.8109073125216617
    },
    {
      "id": "miaminewtimes.com",
      "size": 979,
      "name": "Miami New Times",
      "favicon": "http://miaminewtimes.com/theme/mia/apple-touch-icon.png",
      "avg_tone": -1.8257773848529575
    },
    {
      "id": "nbclosangeles.com",
      "size": 2672,
      "name": "NBC Los Angeles",
      "favicon": "https://media.nbclosangeles.com/designimages/favicon-la.ico",
      "avg_tone": -3.491899934954519
    },
    {
      "id": "nbcwashington.com",
      "size": 2905,
      "name": "NBC4 Washington",
      "favicon": "https://media.nbcwashington.com/designimages/favicon-dc.ico",
      "avg_tone": -3.294849655020785
    },
    {
      "id": "chicagotribune.com",
      "size": 38323,
      "name": "Chicago Tribune",
      "favicon": null,
      "avg_tone": -2.2750019315566563
    },
    {
      "id": "huffingtonpost.com",
      "size": 15383,
      "name": "The Huffington Post",
      "favicon": "https://s.m.huffpost.com/assets/favicon-2020e123c064086aad150fe909c53771f862d7c76cd62f6146e81d533845fd7d.ico",
      "avg_tone": -2.7477563146344117
    },
    {
      "id": "nbcphiladelphia.com",
      "size": 2087,
      "name": "NBC 10 Philadelphia ",
      "favicon": "https://media.nbcphiladelphia.com/designimages/favicon-phi.ico",
      "avg_tone": -3.7428623220505
    }
  ],
  "edges": [
    {
      "source": "npr.org",
      "target": "nbcnews.com",
      "weight": 0.014222317275303428,
      "tone_diff": 2.446391398862897
    },
    {
      "source": "npr.org",
      "target": "stltoday.com",
      "weight": 0.010693471635566486,
      "tone_diff": 2.5263751310835314
    },
    {
      "source": "npr.org",
      "target": "foxnews.com",
      "weight": 0.01122814521734481,
      "tone_diff": 2.6885727181238805
    },
    {
      "source": "npr.org",
      "target": "theonion.com",
      "weight": 0.012658227848101266,
      "tone_diff": 1.3100408429152477
    },
    {
      "source": "kdvr.com",
      "target": "nbcnews.com",
      "weight": 0.021693491952414275,
      "tone_diff": 1.8237981225401012
    },
    {
      "source": "kdvr.com",
      "target": "cbsnews.com",
      "weight": 0.017669699090272918,
      "tone_diff": 1.4569591292869293
    },
    {
      "source": "kdvr.com",
      "target": "nydailynews.com",
      "weight": 0.028166550034989503,
      "tone_diff": 1.0706033720421908
    },
    {
      "source": "kdvr.com",
      "target": "seattletimes.com",
      "weight": 0.025542337298810357,
      "tone_diff": 1.3115388701513453
    },
    {
      "source": "kdvr.com",
      "target": "kron4.com",
      "weight": 0.015220433869839048,
      "tone_diff": 0.6648209566547119
    },
    {
      "source": "kdvr.com",
      "target": "usatoday.com",
      "weight": 0.010321903428971308,
      "tone_diff": 2.2657466396895316
    },
    {
      "source": "kdvr.com",
      "target": "newsday.com",
      "weight": 0.01749475157452764,
      "tone_diff": 0.9634623779885488
    },
    {
      "source": "kdvr.com",
      "target": "ktla.com",
      "weight": 0.01801959412176347,
      "tone_diff": 0.590522483170533
    },
    {
      "source": "kdvr.com",
      "target": "abc13.com",
      "weight": 0.015220433869839048,
      "tone_diff": 1.3205414258015054
    },
    {
      "source": "kdvr.com",
      "target": "wtop.com",
      "weight": 0.019769069279216234,
      "tone_diff": 0.7697785409397739
    },
    {
      "source": "kdvr.com",
      "target": "latimes.com",
      "weight": 0.012421273617914626,
      "tone_diff": 1.8093023490740663
    },
    {
      "source": "kdvr.com",
      "target": "bostonherald.com",
      "weight": 0.032015395381385585,
      "tone_diff": 0.8105305600182193
    },
    {
      "source": "kdvr.com",
      "target": "chicagotribune.com",
      "weight": 0.02641707487753674,
      "tone_diff": 1.7183479093075302
    },
    {
      "source": "kdvr.com",
      "target": "philly.com",
      "weight": 0.018369489153254023,
      "tone_diff": 0.7593176518927424
    },
    {
      "source": "kdvr.com",
      "target": "stltoday.com",
      "weight": 0.05895731280615815,
      "tone_diff": 0.9512351350719168
    },
    {
      "source": "kdvr.com",
      "target": "seattlepi.com",
      "weight": 0.029916025192442266,
      "tone_diff": 1.0383918765872944
    },
    {
      "source": "kdvr.com",
      "target": "boston.com",
      "weight": 0.01801959412176347,
      "tone_diff": 0.7385529750791978
    },
    {
      "source": "kdvr.com",
      "target": "fox2now.com",
      "weight": 0.021868439468159553,
      "tone_diff": 0.42268100606798636
    },
    {
      "source": "kdvr.com",
      "target": "foxnews.com",
      "weight": 0.02799160251924423,
      "tone_diff": 1.454111077384351
    },
    {
      "source": "kdvr.com",
      "target": "miamiherald.com",
      "weight": 0.02729181245626312,
      "tone_diff": 1.238660236363769
    },
    {
      "source": "kdvr.com",
      "target": "newsmax.com",
      "weight": 0.020643806857942617,
      "tone_diff": 1.009088816211976
    },
    {
      "source": "kdvr.com",
      "target": "wgntv.com",
      "weight": 0.030615815255423375,
      "tone_diff": 0.3698087042768392
    },
    {
      "source": "kdvr.com",
      "target": "abc7news.com",
      "weight": 0.018369489153254023,
      "tone_diff": 1.19030536702364
    },
    {
      "source": "ktla.com",
      "target": "nbcnews.com",
      "weight": 0.019614998631511723,
      "tone_diff": 1.8855194840674103
    },
    {
      "source": "ktla.com",
      "target": "nydailynews.com",
      "weight": 0.010856673661162303,
      "tone_diff": 1.9358986935696325
    },
    {
      "source": "ktla.com",
      "target": "seattletimes.com",
      "weight": 0.015509533801660433,
      "tone_diff": 1.8293495192940417
    },
    {
      "source": "ktla.com",
      "target": "kron4.com",
      "weight": 0.010961907371882707,
      "tone_diff": 1.1930900243958453
    },
    {
      "source": "ktla.com",
      "target": "latimes.com",
      "weight": 0.01195146428245598,
      "tone_diff": 2.5853701289503768
    },
    {
      "source": "ktla.com",
      "target": "bostonherald.com",
      "weight": 0.01368488276617097,
      "tone_diff": 1.471126352147491
    },
    {
      "source": "ktla.com",
      "target": "stltoday.com",
      "weight": 0.03266125353526138,
      "tone_diff": 1.1858674377535219
    },
    {
      "source": "ktla.com",
      "target": "seattlepi.com",
      "weight": 0.01569199890520938,
      "tone_diff": 1.6237784956736763
    },
    {
      "source": "ktla.com",
      "target": "fox2now.com",
      "weight": 0.030326253558134442,
      "tone_diff": 0.5735416490567624
    },
    {
      "source": "ktla.com",
      "target": "foxnews.com",
      "weight": 0.017060487181826477,
      "tone_diff": 2.033288882801311
    },
    {
      "source": "ktla.com",
      "target": "miamiherald.com",
      "weight": 0.013776115317945443,
      "tone_diff": 1.5636880501722432
    },
    {
      "source": "ktla.com",
      "target": "newsmax.com",
      "weight": 0.013593650214396496,
      "tone_diff": 1.866189461901682
    },
    {
      "source": "ktla.com",
      "target": "wgntv.com",
      "weight": 0.024696835255841466,
      "tone_diff": 0.4600837907292728
    },
    {
      "source": "kxan.com",
      "target": "nbcnews.com",
      "weight": 0.02069925204383371,
      "tone_diff": 2.0263735098283977
    },
    {
      "source": "kxan.com",
      "target": "cbsnews.com",
      "weight": 0.015828839798225778,
      "tone_diff": 1.4896177873425662
    },
    {
      "source": "kxan.com",
      "target": "nydailynews.com",
      "weight": 0.029918246651591582,
      "tone_diff": 0.9923515191078388
    },
    {
      "source": "kxan.com",
      "target": "seattletimes.com",
      "weight": 0.04174639067663941,
      "tone_diff": 0.9156257703000547
    },
    {
      "source": "kxan.com",
      "target": "kron4.com",
      "weight": 0.013045747086449818,
      "tone_diff": 0.6498118270434022
    },
    {
      "source": "kxan.com",
      "target": "newsday.com",
      "weight": 0.017394329448599758,
      "tone_diff": 0.6054279977450192
    },
    {
      "source": "kxan.com",
      "target": "abc13.com",
      "weight": 0.013219690380935815,
      "tone_diff": 1.955031790648086
    },
    {
      "source": "kxan.com",
      "target": "wtop.com",
      "weight": 0.032527396068881546,
      "tone_diff": 0.7891271411335461
    },
    {
      "source": "kxan.com",
      "target": "bostonherald.com",
      "weight": 0.04713863280570534,
      "tone_diff": 0.6370634165109071
    },
    {
      "source": "kxan.com",
      "target": "chicagotribune.com",
      "weight": 0.020177422160375717,
      "tone_diff": 0.9612445641508597
    },
    {
      "source": "kxan.com",
      "target": "philly.com",
      "weight": 0.022438684988693686,
      "tone_diff": 0.8220529972842151
    },
    {
      "source": "kxan.com",
      "target": "stltoday.com",
      "weight": 0.06992520438337102,
      "tone_diff": 0.7013895031919911
    },
    {
      "source": "kxan.com",
      "target": "seattlepi.com",
      "weight": 0.04244216385458341,
      "tone_diff": 0.9509005485386108
    },
    {
      "source": "kxan.com",
      "target": "boston.com",
      "weight": 0.0142633501478518,
      "tone_diff": 0.7628448438556864
    },
    {
      "source": "kxan.com",
      "target": "foxnews.com",
      "weight": 0.02939641676813359,
      "tone_diff": 1.6617623859458195
    },
    {
      "source": "kxan.com",
      "target": "miamiherald.com",
      "weight": 0.033049225952339535,
      "tone_diff": 0.8534278749451413
    },
    {
      "source": "kxan.com",
      "target": "newsmax.com",
      "weight": 0.017568272743085755,
      "tone_diff": 1.1897741369911607
    },
    {
      "source": "kxan.com",
      "target": "nypost.com",
      "weight": 0.010958427552617847,
      "tone_diff": 1.6941253379780086
    },
    {
      "source": "kxan.com",
      "target": "abc7news.com",
      "weight": 0.013045747086449818,
      "tone_diff": 1.767536826035121
    },
    {
      "source": "wtop.com",
      "target": "nbcnews.com",
      "weight": 0.01264939775845231,
      "tone_diff": 1.7204307073474951
    },
    {
      "source": "wtop.com",
      "target": "cbsnews.com",
      "weight": 0.01953755859298066,
      "tone_diff": 1.0197841417264242
    },
    {
      "source": "wtop.com",
      "target": "nydailynews.com",
      "weight": 0.04545877319443799,
      "tone_diff": 0.7113585969322159
    },
    {
      "source": "wtop.com",
      "target": "seattletimes.com",
      "weight": 0.07478026321908571,
      "tone_diff": 0.6495436059558601
    },
    {
      "source": "wtop.com",
      "target": "kron4.com",
      "weight": 0.026856673061112633,
      "tone_diff": 0.8394529701415961
    },
    {
      "source": "wtop.com",
      "target": "newsday.com",
      "weight": 0.020985551832115586,
      "tone_diff": 0.7173844315301537
    },
    {
      "source": "wtop.com",
      "target": "nbcchicago.com",
      "weight": 0.03552440792653456,
      "tone_diff": 0.523685651509535
    },
    {
      "source": "wtop.com",
      "target": "denverpost.com",
      "weight": 0.015828677839851025,
      "tone_diff": 0.8928133406197345
    },
    {
      "source": "wtop.com",
      "target": "nbcsandiego.com",
      "weight": 0.03728813559322034,
      "tone_diff": 0.46451045396490115
    },
    {
      "source": "wtop.com",
      "target": "twincities.com",
      "weight": 0.023047375160051217,
      "tone_diff": 0.5495094521786955
    },
    {
      "source": "wtop.com",
      "target": "mercurynews.com",
      "weight": 0.015001734304543877,
      "tone_diff": 1.0966068055843157
    },
    {
      "source": "wtop.com",
      "target": "bostonherald.com",
      "weight": 0.035888254035124675,
      "tone_diff": 0.6466723086248461
    },
    {
      "source": "wtop.com",
      "target": "chicagotribune.com",
      "weight": 0.015183927824024555,
      "tone_diff": 0.8629167450591017
    },
    {
      "source": "wtop.com",
      "target": "nytimes.com",
      "weight": 0.012044830953820397,
      "tone_diff": 1.1332758942411931
    },
    {
      "source": "wtop.com",
      "target": "philly.com",
      "weight": 0.02098196912699442,
      "tone_diff": 0.5827881106604214
    },
    {
      "source": "wtop.com",
      "target": "stltoday.com",
      "weight": 0.0740594335674092,
      "tone_diff": 0.6052105102487382
    },
    {
      "source": "wtop.com",
      "target": "seattlepi.com",
      "weight": 0.08842952146212156,
      "tone_diff": 0.5886861884816884
    },
    {
      "source": "wtop.com",
      "target": "boston.com",
      "weight": 0.043881145657834277,
      "tone_diff": 0.4661097786020202
    },
    {
      "source": "wtop.com",
      "target": "foxnews.com",
      "weight": 0.052783332558247686,
      "tone_diff": 0.6467234436398319
    },
    {
      "source": "wtop.com",
      "target": "nbclosangeles.com",
      "weight": 0.03113747087481466,
      "tone_diff": 0.6130575348749513
    },
    {
      "source": "wtop.com",
      "target": "nbcphiladelphia.com",
      "weight": 0.03256086828982106,
      "tone_diff": 0.5069913489402219
    },
    {
      "source": "wtop.com",
      "target": "miamiherald.com",
      "weight": 0.09159187090173464,
      "tone_diff": 0.7390057865151506
    },
    {
      "source": "wtop.com",
      "target": "newsmax.com",
      "weight": 0.020089471783044818,
      "tone_diff": 0.8727019362639415
    },
    {
      "source": "wtop.com",
      "target": "wgntv.com",
      "weight": 0.017450458444247263,
      "tone_diff": 1.1920077661287385
    },
    {
      "source": "wtop.com",
      "target": "nbcwashington.com",
      "weight": 0.040174513724777317,
      "tone_diff": 0.5743441680191517
    },
    {
      "source": "wtop.com",
      "target": "nbcnewyork.com",
      "weight": 0.03232887647176212,
      "tone_diff": 0.6171523089355332
    },
    {
      "source": "wtop.com",
      "target": "theonion.com",
      "weight": 0.012658227848101266,
      "tone_diff": 1.8437095215493704
    },
    {
      "source": "wtop.com",
      "target": "nypost.com",
      "weight": 0.011141947596114603,
      "tone_diff": 1.421033920570332
    },
    {
      "source": "wtop.com",
      "target": "abc7news.com",
      "weight": 0.010313952170463561,
      "tone_diff": 1.4856874974455168
    },
    {
      "source": "abc13.com",
      "target": "nbcnews.com",
      "weight": 0.021944877795111804,
      "tone_diff": 2.163067024226332
    },
    {
      "source": "abc13.com",
      "target": "cbsnews.com",
      "weight": 0.010868434737389496,
      "tone_diff": 1.9413603881573365
    },
    {
      "source": "abc13.com",
      "target": "nydailynews.com",
      "weight": 0.018668746749869996,
      "tone_diff": 1.9002733517323038
    },
    {
      "source": "abc13.com",
      "target": "seattletimes.com",
      "weight": 0.016068642745709828,
      "tone_diff": 2.2010268017476284
    },
    {
      "source": "abc13.com",
      "target": "kron4.com",
      "weight": 0.01534667032063579,
      "tone_diff": 1.1808097641049382
    },
    {
      "source": "abc13.com",
      "target": "nbcsandiego.com",
      "weight": 0.010691003911342895,
      "tone_diff": 1.3688866542821605
    },
    {
      "source": "abc13.com",
      "target": "bostonherald.com",
      "weight": 0.015964638585543423,
      "tone_diff": 1.513162020360678
    },
    {
      "source": "abc13.com",
      "target": "chicagotribune.com",
      "weight": 0.010452418096723868,
      "tone_diff": 1.9041254426699494
    },
    {
      "source": "abc13.com",
      "target": "stltoday.com",
      "weight": 0.027457098283931357,
      "tone_diff": 1.6258674871533845
    },
    {
      "source": "abc13.com",
      "target": "seattlepi.com",
      "weight": 0.016536661466458658,
      "tone_diff": 1.877533709457721
    },
    {
      "source": "abc13.com",
      "target": "foxnews.com",
      "weight": 0.020904836193447737,
      "tone_diff": 2.130219055921063
    },
    {
      "source": "abc13.com",
      "target": "nbcphiladelphia.com",
      "weight": 0.01026694045174538,
      "tone_diff": 1.3477505480246925
    },
    {
      "source": "abc13.com",
      "target": "miamiherald.com",
      "weight": 0.014508580343213728,
      "tone_diff": 1.7669467398945595
    },
    {
      "source": "abc13.com",
      "target": "newsmax.com",
      "weight": 0.01107644305772231,
      "tone_diff": 1.9900075614198254
    },
    {
      "source": "abc13.com",
      "target": "wgntv.com",
      "weight": 0.012126589766341319,
      "tone_diff": 1.5058399769798219
    },
    {
      "source": "abc13.com",
      "target": "abc7news.com",
      "weight": 0.16536325512864106,
      "tone_diff": 0.21275716027843608
    },
    {
      "source": "kron4.com",
      "target": "nbcnews.com",
      "weight": 0.023020005480953686,
      "tone_diff": 1.796933413554306
    },
    {
      "source": "kron4.com",
      "target": "cbsnews.com",
      "weight": 0.020827624006577145,
      "tone_diff": 1.497282063699653
    },
    {
      "source": "kron4.com",
      "target": "nydailynews.com",
      "weight": 0.036996437380104136,
      "tone_diff": 0.9866810551777077
    },
    {
      "source": "kron4.com",
      "target": "seattletimes.com",
      "weight": 0.03631131816936147,
      "tone_diff": 1.1318324734182479
    },
    {
      "source": "kron4.com",
      "target": "newsday.com",
      "weight": 0.018635242532200603,
      "tone_diff": 0.8214172476197917
    },
    {
      "source": "kron4.com",
      "target": "nbcsandiego.com",
      "weight": 0.010169491525423728,
      "tone_diff": 0.9322901585691303
    },
    {
      "source": "kron4.com",
      "target": "latimes.com",
      "weight": 0.01918333790079474,
      "tone_diff": 1.9358715655988248
    },
    {
      "source": "kron4.com",
      "target": "twincities.com",
      "weight": 0.014084507042253521,
      "tone_diff": 0.759037229822381
    },
    {
      "source": "kron4.com",
      "target": "mercurynews.com",
      "weight": 0.010276788161140039,
      "tone_diff": 0.8809145069832431
    },
    {
      "source": "kron4.com",
      "target": "bostonherald.com",
      "weight": 0.0441216771718279,
      "tone_diff": 0.8471956168583359
    },
    {
      "source": "kron4.com",
      "target": "chicagotribune.com",
      "weight": 0.025212386955330228,
      "tone_diff": 1.253712679127689
    },
    {
      "source": "kron4.com",
      "target": "philly.com",
      "weight": 0.025212386955330228,
      "tone_diff": 0.7262604085572298
    },
    {
      "source": "kron4.com",
      "target": "stltoday.com",
      "weight": 0.06741573033707865,
      "tone_diff": 0.9265620169102347
    },
    {
      "source": "kron4.com",
      "target": "seattlepi.com",
      "weight": 0.04425870101397643,
      "tone_diff": 1.0287714034631437
    },
    {
      "source": "kron4.com",
      "target": "boston.com",
      "weight": 0.021238695533022746,
      "tone_diff": 0.6735177242517081
    },
    {
      "source": "kron4.com",
      "target": "foxnews.com",
      "weight": 0.033296793642093724,
      "tone_diff": 1.708769715664984
    },
    {
      "source": "kron4.com",
      "target": "nbclosangeles.com",
      "weight": 0.011438254607074773,
      "tone_diff": 0.6539759847757117
    },
    {
      "source": "kron4.com",
      "target": "miamiherald.com",
      "weight": 0.0348040559057276,
      "tone_diff": 1.0413791575974882
    },
    {
      "source": "kron4.com",
      "target": "newsmax.com",
      "weight": 0.021238695533022746,
      "tone_diff": 1.1893849329678439
    },
    {
      "source": "kron4.com",
      "target": "wgntv.com",
      "weight": 0.011978704525288377,
      "tone_diff": 0.5050828399475771
    },
    {
      "source": "kron4.com",
      "target": "nypost.com",
      "weight": 0.012880241161962182,
      "tone_diff": 1.2951843815615491
    },
    {
      "source": "kron4.com",
      "target": "abc7news.com",
      "weight": 0.020827624006577145,
      "tone_diff": 1.3886527369802106
    },
    {
      "source": "wgntv.com",
      "target": "nbcnews.com",
      "weight": 0.019964507542147295,
      "tone_diff": 2.1168098375211795
    },
    {
      "source": "wgntv.com",
      "target": "cbsnews.com",
      "weight": 0.013161786453711919,
      "tone_diff": 1.361785850738052
    },
    {
      "source": "wgntv.com",
      "target": "nydailynews.com",
      "weight": 0.02085181898846495,
      "tone_diff": 1.3430231867891869
    },
    {
      "source": "wgntv.com",
      "target": "seattletimes.com",
      "weight": 0.026175687666370896,
      "tone_diff": 1.3011307438951836
    },
    {
      "source": "wgntv.com",
      "target": "usatoday.com",
      "weight": 0.012422360248447204,
      "tone_diff": 2.492862889589486
    },
    {
      "source": "wgntv.com",
      "target": "newsday.com",
      "weight": 0.012718130730553091,
      "tone_diff": 1.029332649967462
    },
    {
      "source": "wgntv.com",
      "target": "latimes.com",
      "weight": 0.01168293404318249,
      "tone_diff": 1.8005238824368135
    },
    {
      "source": "wgntv.com",
      "target": "bostonherald.com",
      "weight": 0.025879917184265012,
      "tone_diff": 0.7982739987099905
    },
    {
      "source": "wgntv.com",
      "target": "chicagotribune.com",
      "weight": 0.030020703933747412,
      "tone_diff": 2.0505590904133366
    },
    {
      "source": "wgntv.com",
      "target": "philly.com",
      "weight": 0.01567583555161195,
      "tone_diff": 1.061261820353906
    },
    {
      "source": "wgntv.com",
      "target": "stltoday.com",
      "weight": 0.04924578527062999,
      "tone_diff": 1.0717097685728987
    },
    {
      "source": "wgntv.com",
      "target": "seattlepi.com",
      "weight": 0.030168589174800354,
      "tone_diff": 1.2508110125302077
    },
    {
      "source": "wgntv.com",
      "target": "boston.com",
      "weight": 0.01168293404318249,
      "tone_diff": 0.6761840879507429
    },
    {
      "source": "wgntv.com",
      "target": "fox2now.com",
      "weight": 0.04599230996746525,
      "tone_diff": 0.29117817710253086
    },
    {
      "source": "wgntv.com",
      "target": "foxnews.com",
      "weight": 0.023809523809523808,
      "tone_diff": 1.9607186142628066
    },
    {
      "source": "wgntv.com",
      "target": "miamiherald.com",
      "weight": 0.023957409050576754,
      "tone_diff": 1.275211076825274
    },
    {
      "source": "wgntv.com",
      "target": "newsmax.com",
      "weight": 0.012718130730553091,
      "tone_diff": 1.3664008315451153
    },
    {
      "source": "wgntv.com",
      "target": "abc7news.com",
      "weight": 0.011535048802129548,
      "tone_diff": 1.5984522824486336
    },
    {
      "source": "boston.com",
      "target": "nbcnews.com",
      "weight": 0.025271863991422883,
      "tone_diff": 1.797088542096688
    },
    {
      "source": "boston.com",
      "target": "cbsnews.com",
      "weight": 0.02282125899831521,
      "tone_diff": 0.9679112732952505
    },
    {
      "source": "boston.com",
      "target": "nydailynews.com",
      "weight": 0.03966916832593046,
      "tone_diff": 0.7207897795106817
    },
    {
      "source": "boston.com",
      "target": "seattletimes.com",
      "weight": 0.0823250114872109,
      "tone_diff": 0.548631884482513
    },
    {
      "source": "boston.com",
      "target": "usatoday.com",
      "weight": 0.01133404809312299,
      "tone_diff": 2.1223216548850865
    },
    {
      "source": "boston.com",
      "target": "newsday.com",
      "weight": 0.014933374176749885,
      "tone_diff": 0.8486203198901974
    },
    {
      "source": "boston.com",
      "target": "denverpost.com",
      "weight": 0.010552451893234015,
      "tone_diff": 0.7890925273777246
    },
    {
      "source": "boston.com",
      "target": "nbcsandiego.com",
      "weight": 0.013298565840938721,
      "tone_diff": 0.6891416623094709
    },
    {
      "source": "boston.com",
      "target": "twincities.com",
      "weight": 0.016645326504481434,
      "tone_diff": 0.4830528586873197
    },
    {
      "source": "boston.com",
      "target": "mercurynews.com",
      "weight": 0.01023239680887964,
      "tone_diff": 0.9370362924578085
    },
    {
      "source": "boston.com",
      "target": "bostonherald.com",
      "weight": 0.059044264052688006,
      "tone_diff": 0.7063648427255914
    },
    {
      "source": "boston.com",
      "target": "chicagotribune.com",
      "weight": 0.022438351968142135,
      "tone_diff": 0.990017390749917
    },
    {
      "source": "boston.com",
      "target": "nytimes.com",
      "weight": 0.01516311839485373,
      "tone_diff": 1.4314289263856377
    },
    {
      "source": "boston.com",
      "target": "philly.com",
      "weight": 0.030096492571603614,
      "tone_diff": 0.6640015672618654
    },
    {
      "source": "boston.com",
      "target": "stltoday.com",
      "weight": 0.08837494256394547,
      "tone_diff": 0.5713352974654777
    },
    {
      "source": "boston.com",
      "target": "seattlepi.com",
      "weight": 0.09595650176137234,
      "tone_diff": 0.5917430115149924
    },
    {
      "source": "boston.com",
      "target": "foxnews.com",
      "weight": 0.03499770255781896,
      "tone_diff": 1.1310545822121287
    },
    {
      "source": "boston.com",
      "target": "nbclosangeles.com",
      "weight": 0.014615547553484431,
      "tone_diff": 0.7293342211516985
    },
    {
      "source": "boston.com",
      "target": "nbcphiladelphia.com",
      "weight": 0.01496039894397184,
      "tone_diff": 0.6708993633936948
    },
    {
      "source": "boston.com",
      "target": "politico.com",
      "weight": 0.011640373717261449,
      "tone_diff": 2.25839842998416
    },
    {
      "source": "boston.com",
      "target": "miamiherald.com",
      "weight": 0.04441721550007658,
      "tone_diff": 0.7538626812166485
    },
    {
      "source": "boston.com",
      "target": "newsmax.com",
      "weight": 0.024199724306938276,
      "tone_diff": 1.1818996536387687
    },
    {
      "source": "boston.com",
      "target": "nbcwashington.com",
      "weight": 0.014906380658062171,
      "tone_diff": 0.5423136213051164
    },
    {
      "source": "boston.com",
      "target": "nbcnewyork.com",
      "weight": 0.017361804031131512,
      "tone_diff": 0.9156601164058052
    },
    {
      "source": "boston.com",
      "target": "abc7news.com",
      "weight": 0.012253024965538368,
      "tone_diff": 1.4100380477613368
    },
    {
      "source": "nypost.com",
      "target": "nbcnews.com",
      "weight": 0.01775365276303975,
      "tone_diff": 2.2000459113696906
    },
    {
      "source": "nypost.com",
      "target": "cbsnews.com",
      "weight": 0.010733817647538977,
      "tone_diff": 1.4516775876935069
    },
    {
      "source": "nypost.com",
      "target": "nydailynews.com",
      "weight": 0.017345522814464127,
      "tone_diff": 1.9552440292058249
    },
    {
      "source": "nypost.com",
      "target": "seattletimes.com",
      "weight": 0.020284058444208636,
      "tone_diff": 1.9074583656116537
    },
    {
      "source": "nypost.com",
      "target": "villagevoice.com",
      "weight": 0.011876484560570071,
      "tone_diff": 2.9525301011867184
    },
    {
      "source": "nypost.com",
      "target": "nbcsandiego.com",
      "weight": 0.012777053455019557,
      "tone_diff": 1.6050086500025011
    },
    {
      "source": "nypost.com",
      "target": "bostonherald.com",
      "weight": 0.011794955513835605,
      "tone_diff": 1.7452918932057937
    },
    {
      "source": "nypost.com",
      "target": "chicagotribune.com",
      "weight": 0.010448126683536037,
      "tone_diff": 1.827479575255405
    },
    {
      "source": "nypost.com",
      "target": "stltoday.com",
      "weight": 0.021018692351644764,
      "tone_diff": 1.5980625930156733
    },
    {
      "source": "nypost.com",
      "target": "seattlepi.com",
      "weight": 0.017998530732185127,
      "tone_diff": 1.1579344722911156
    },
    {
      "source": "nypost.com",
      "target": "foxnews.com",
      "weight": 0.02620194269855522,
      "tone_diff": 1.497498385621173
    },
    {
      "source": "nypost.com",
      "target": "miamiherald.com",
      "weight": 0.016447636927597747,
      "tone_diff": 1.5857589233873115
    },
    {
      "source": "nypost.com",
      "target": "newsmax.com",
      "weight": 0.011141947596114603,
      "tone_diff": 1.7866058266948244
    },
    {
      "source": "nypost.com",
      "target": "nbcwashington.com",
      "weight": 0.011088892928558443,
      "tone_diff": 1.4424464019614496
    },
    {
      "source": "nypost.com",
      "target": "nbcnewyork.com",
      "weight": 0.012572340850129714,
      "tone_diff": 1.5080744884997317
    },
    {
      "source": "philly.com",
      "target": "nbcnews.com",
      "weight": 0.016701258269555066,
      "tone_diff": 1.78189818499598
    },
    {
      "source": "philly.com",
      "target": "cbsnews.com",
      "weight": 0.011620120534131643,
      "tone_diff": 1.3282379689858614
    },
    {
      "source": "philly.com",
      "target": "nydailynews.com",
      "weight": 0.027694902062524323,
      "tone_diff": 0.9435315928138548
    },
    {
      "source": "philly.com",
      "target": "seattletimes.com",
      "weight": 0.031618887015177066,
      "tone_diff": 1.0478882286995712
    },
    {
      "source": "philly.com",
      "target": "newsday.com",
      "weight": 0.01455803988353568,
      "tone_diff": 0.8233767010608984
    },
    {
      "source": "philly.com",
      "target": "nbcchicago.com",
      "weight": 0.01570807153214113,
      "tone_diff": 0.6378323401780938
    },
    {
      "source": "philly.com",
      "target": "denverpost.com",
      "weight": 0.02307055659010966,
      "tone_diff": 0.7031023108880474
    },
    {
      "source": "philly.com",
      "target": "nbcsandiego.com",
      "weight": 0.017209908735332465,
      "tone_diff": 0.980308057050266
    },
    {
      "source": "philly.com",
      "target": "latimes.com",
      "weight": 0.010182903100272409,
      "tone_diff": 1.2177700044286341
    },
    {
      "source": "philly.com",
      "target": "twincities.com",
      "weight": 0.03201024327784891,
      "tone_diff": 0.6239684328962724
    },
    {
      "source": "philly.com",
      "target": "mercurynews.com",
      "weight": 0.02098508498092265,
      "tone_diff": 1.0238930433523863
    },
    {
      "source": "philly.com",
      "target": "bostonherald.com",
      "weight": 0.029024516798547152,
      "tone_diff": 0.7530324304439528
    },
    {
      "source": "philly.com",
      "target": "chicagotribune.com",
      "weight": 0.019036191464521988,
      "tone_diff": 0.8856866710829422
    },
    {
      "source": "philly.com",
      "target": "phillyvoice.com",
      "weight": 0.023752969121140142,
      "tone_diff": 2.3491527180900578
    },
    {
      "source": "philly.com",
      "target": "stltoday.com",
      "weight": 0.0410234790504605,
      "tone_diff": 0.7799115128297835
    },
    {
      "source": "philly.com",
      "target": "seattlepi.com",
      "weight": 0.032429627707873915,
      "tone_diff": 0.8292555956170264
    },
    {
      "source": "philly.com",
      "target": "foxnews.com",
      "weight": 0.022408872746140875,
      "tone_diff": 1.3687293881327198
    },
    {
      "source": "philly.com",
      "target": "nbclosangeles.com",
      "weight": 0.01673374285109087,
      "tone_diff": 0.9336618256684961
    },
    {
      "source": "philly.com",
      "target": "nbcphiladelphia.com",
      "weight": 0.02552068055148137,
      "tone_diff": 0.97171091074044
    },
    {
      "source": "philly.com",
      "target": "miamiherald.com",
      "weight": 0.022895317161758983,
      "tone_diff": 0.9747277227641618
    },
    {
      "source": "philly.com",
      "target": "newsmax.com",
      "weight": 0.014690621351666882,
      "tone_diff": 1.2068372251318558
    },
    {
      "source": "philly.com",
      "target": "nbcwashington.com",
      "weight": 0.025449918196691512,
      "tone_diff": 0.7785234731842282
    },
    {
      "source": "philly.com",
      "target": "nbcnewyork.com",
      "weight": 0.017361804031131512,
      "tone_diff": 0.9685329275274505
    },
    {
      "source": "philly.com",
      "target": "theonion.com",
      "weight": 0.012658227848101266,
      "tone_diff": 1.5124087354746611
    },
    {
      "source": "philly.com",
      "target": "abc7news.com",
      "weight": 0.01144735350787714,
      "tone_diff": 1.7523397116520438
    },
    {
      "source": "cbsnews.com",
      "target": "nbcnews.com",
      "weight": 0.023594753220152045,
      "tone_diff": 1.7973918197164258
    },
    {
      "source": "cbsnews.com",
      "target": "nydailynews.com",
      "weight": 0.029306337889470988,
      "tone_diff": 1.2225371137620598
    },
    {
      "source": "cbsnews.com",
      "target": "seattletimes.com",
      "weight": 0.03222121558277859,
      "tone_diff": 1.1790076216001024
    },
    {
      "source": "cbsnews.com",
      "target": "usatoday.com",
      "weight": 0.010792925513057864,
      "tone_diff": 1.9035693790301407
    },
    {
      "source": "cbsnews.com",
      "target": "newsday.com",
      "weight": 0.014283359885733121,
      "tone_diff": 0.9722537141722216
    },
    {
      "source": "cbsnews.com",
      "target": "nbcchicago.com",
      "weight": 0.016433059449009184,
      "tone_diff": 0.9963094067094346
    },
    {
      "source": "cbsnews.com",
      "target": "denverpost.com",
      "weight": 0.0111731843575419,
      "tone_diff": 1.0741933771934153
    },
    {
      "source": "cbsnews.com",
      "target": "nbcsandiego.com",
      "weight": 0.02346805736636245,
      "tone_diff": 0.7599292501808684
    },
    {
      "source": "cbsnews.com",
      "target": "latimes.com",
      "weight": 0.01126560838224288,
      "tone_diff": 1.399802946172403
    },
    {
      "source": "cbsnews.com",
      "target": "twincities.com",
      "weight": 0.015364916773367477,
      "tone_diff": 1.068785638259708
    },
    {
      "source": "cbsnews.com",
      "target": "mercurynews.com",
      "weight": 0.013180714533472077,
      "tone_diff": 1.3390095568229636
    },
    {
      "source": "cbsnews.com",
      "target": "bostonherald.com",
      "weight": 0.022255485090794502,
      "tone_diff": 1.02784280215577
    },
    {
      "source": "cbsnews.com",
      "target": "chicagotribune.com",
      "weight": 0.017331705203450586,
      "tone_diff": 1.3610815178195201
    },
    {
      "source": "cbsnews.com",
      "target": "stltoday.com",
      "weight": 0.04080828770630638,
      "tone_diff": 1.0802256501787084
    },
    {
      "source": "cbsnews.com",
      "target": "seattlepi.com",
      "weight": 0.03434828849411116,
      "tone_diff": 0.9663147079471581
    },
    {
      "source": "cbsnews.com",
      "target": "foxnews.com",
      "weight": 0.02910938669397723,
      "tone_diff": 1.7180003005626172
    },
    {
      "source": "cbsnews.com",
      "target": "nbclosangeles.com",
      "weight": 0.021393772505825037,
      "tone_diff": 1.0072637250163499
    },
    {
      "source": "cbsnews.com",
      "target": "nbcphiladelphia.com",
      "weight": 0.014373716632443531,
      "tone_diff": 0.9317066559017358
    },
    {
      "source": "cbsnews.com",
      "target": "miamiherald.com",
      "weight": 0.02910938669397723,
      "tone_diff": 1.1546244419825165
    },
    {
      "source": "cbsnews.com",
      "target": "newsmax.com",
      "weight": 0.018434631898215623,
      "tone_diff": 1.4525493986359979
    },
    {
      "source": "cbsnews.com",
      "target": "nbcwashington.com",
      "weight": 0.022359570987093257,
      "tone_diff": 0.8990753172397831
    },
    {
      "source": "cbsnews.com",
      "target": "nbcnewyork.com",
      "weight": 0.018958291758132108,
      "tone_diff": 1.3814420666955454
    },
    {
      "source": "cbsnews.com",
      "target": "abc7news.com",
      "weight": 0.011674033775359855,
      "tone_diff": 1.8352019115757117
    },
    {
      "source": "fox2now.com",
      "target": "nbcnews.com",
      "weight": 0.012261878694985767,
      "tone_diff": 2.1908882081399055
    },
    {
      "source": "fox2now.com",
      "target": "nydailynews.com",
      "weight": 0.010619662798335887,
      "tone_diff": 1.9279549581441495
    },
    {
      "source": "fox2now.com",
      "target": "seattletimes.com",
      "weight": 0.02003503393912853,
      "tone_diff": 2.20318279637391
    },
    {
      "source": "fox2now.com",
      "target": "stltoday.com",
      "weight": 0.05211298445368951,
      "tone_diff": 1.4432902438458945
    },
    {
      "source": "fox2now.com",
      "target": "seattlepi.com",
      "weight": 0.012152397635209108,
      "tone_diff": 1.707486664966144
    },
    {
      "source": "fox2now.com",
      "target": "foxnews.com",
      "weight": 0.01620319684694548,
      "tone_diff": 2.2960469927648828
    },
    {
      "source": "fox2now.com",
      "target": "miamiherald.com",
      "weight": 0.011823954455879132,
      "tone_diff": 2.0446709077615046
    },
    {
      "source": "foxnews.com",
      "target": "nbcnews.com",
      "weight": 0.0136413129916684,
      "tone_diff": 2.240530581218677
    },
    {
      "source": "foxnews.com",
      "target": "nydailynews.com",
      "weight": 0.03384083044982699,
      "tone_diff": 1.4203633461489569
    },
    {
      "source": "foxnews.com",
      "target": "seattletimes.com",
      "weight": 0.041511188323525454,
      "tone_diff": 1.0145087794897287
    },
    {
      "source": "foxnews.com",
      "target": "huffingtonpost.com",
      "weight": 0.017697483639045074,
      "tone_diff": 2.379641298374
    },
    {
      "source": "foxnews.com",
      "target": "usatoday.com",
      "weight": 0.017242435379149823,
      "tone_diff": 2.3802640620077598
    },
    {
      "source": "foxnews.com",
      "target": "villagevoice.com",
      "weight": 0.0166270783847981,
      "tone_diff": 2.820035749856928
    },
    {
      "source": "foxnews.com",
      "target": "newsday.com",
      "weight": 0.021864527825083777,
      "tone_diff": 1.6202175143038084
    },
    {
      "source": "foxnews.com",
      "target": "nbcchicago.com",
      "weight": 0.03069115514741421,
      "tone_diff": 1.1480185261204583
    },
    {
      "source": "foxnews.com",
      "target": "denverpost.com",
      "weight": 0.015518311607697082,
      "tone_diff": 1.7987294986915678
    },
    {
      "source": "foxnews.com",
      "target": "breitbart.com",
      "weight": 0.012859712230215828,
      "tone_diff": 2.2718388815440176
    },
    {
      "source": "foxnews.com",
      "target": "observer.com",
      "weight": 0.015828677839851025,
      "tone_diff": 3.629352393887285
    },
    {
      "source": "foxnews.com",
      "target": "nbcsandiego.com",
      "weight": 0.032073011734028684,
      "tone_diff": 1.2245159368107303
    },
    {
      "source": "foxnews.com",
      "target": "latimes.com",
      "weight": 0.015479193710352935,
      "tone_diff": 2.060962575137008
    },
    {
      "source": "foxnews.com",
      "target": "twincities.com",
      "weight": 0.022535211267605635,
      "tone_diff": 1.7903769852215083
    },
    {
      "source": "foxnews.com",
      "target": "mercurynews.com",
      "weight": 0.02115851543531044,
      "tone_diff": 2.0759478530885462
    },
    {
      "source": "foxnews.com",
      "target": "bostonherald.com",
      "weight": 0.03064851628531557,
      "tone_diff": 1.3763632614481895
    },
    {
      "source": "foxnews.com",
      "target": "chicagotribune.com",
      "weight": 0.017522500978303403,
      "tone_diff": 1.577939219670998
    },
    {
      "source": "foxnews.com",
      "target": "nytimes.com",
      "weight": 0.012135068589518115,
      "tone_diff": 1.9063607105419278
    },
    {
      "source": "foxnews.com",
      "target": "gothamist.com",
      "weight": 0.023622047244094488,
      "tone_diff": 3.024676476725445
    },
    {
      "source": "foxnews.com",
      "target": "phillyvoice.com",
      "weight": 0.012826603325415678,
      "tone_diff": 3.108332516065795
    },
    {
      "source": "foxnews.com",
      "target": "stltoday.com",
      "weight": 0.034922919081691116,
      "tone_diff": 1.0443336851914746
    },
    {
      "source": "foxnews.com",
      "target": "seattlepi.com",
      "weight": 0.052946782935260395,
      "tone_diff": 0.8455485485173219
    },
    {
      "source": "foxnews.com",
      "target": "nbclosangeles.com",
      "weight": 0.024994704511755984,
      "tone_diff": 1.2218355125724254
    },
    {
      "source": "foxnews.com",
      "target": "newsweek.com",
      "weight": 0.013067762672568237,
      "tone_diff": 2.5105450260211093
    },
    {
      "source": "foxnews.com",
      "target": "nbcphiladelphia.com",
      "weight": 0.02992079788794368,
      "tone_diff": 1.4371119535915604
    },
    {
      "source": "foxnews.com",
      "target": "politico.com",
      "weight": 0.014317010706902404,
      "tone_diff": 2.5297113135258167
    },
    {
      "source": "foxnews.com",
      "target": "miamiherald.com",
      "weight": 0.03223754236147644,
      "tone_diff": 1.2319750689782374
    },
    {
      "source": "foxnews.com",
      "target": "newsmax.com",
      "weight": 0.027480619078051625,
      "tone_diff": 1.5901757088635644
    },
    {
      "source": "foxnews.com",
      "target": "nbcwashington.com",
      "weight": 0.03072168696600618,
      "tone_diff": 1.4781055414634632
    },
    {
      "source": "foxnews.com",
      "target": "nbcnewyork.com",
      "weight": 0.03632009578926362,
      "tone_diff": 1.524405595410807
    },
    {
      "source": "foxnews.com",
      "target": "theonion.com",
      "weight": 0.012658227848101266,
      "tone_diff": 2.675391144818058
    },
    {
      "source": "foxnews.com",
      "target": "abc7news.com",
      "weight": 0.02232800634704749,
      "tone_diff": 2.098742488005221
    },
    {
      "source": "latimes.com",
      "target": "nbcnews.com",
      "weight": 0.0144750055107889,
      "tone_diff": 1.9701850350599244
    },
    {
      "source": "latimes.com",
      "target": "nydailynews.com",
      "weight": 0.017708001665482868,
      "tone_diff": 1.4010987557867411
    },
    {
      "source": "latimes.com",
      "target": "seattletimes.com",
      "weight": 0.01675279825614147,
      "tone_diff": 1.5984668992114013
    },
    {
      "source": "latimes.com",
      "target": "newsday.com",
      "weight": 0.012030983903752129,
      "tone_diff": 1.693560371753618
    },
    {
      "source": "latimes.com",
      "target": "laweekly.com",
      "weight": 0.0316622691292876,
      "tone_diff": 3.015061220348723
    },
    {
      "source": "latimes.com",
      "target": "nbcchicago.com",
      "weight": 0.014499758337361043,
      "tone_diff": 0.7673752983487501
    },
    {
      "source": "latimes.com",
      "target": "denverpost.com",
      "weight": 0.012518104696875646,
      "tone_diff": 1.4384671878759445
    },
    {
      "source": "latimes.com",
      "target": "nbcsandiego.com",
      "weight": 0.01877444589308996,
      "tone_diff": 1.1016387394530265
    },
    {
      "source": "latimes.com",
      "target": "mercurynews.com",
      "weight": 0.01422129725979882,
      "tone_diff": 1.7226512197164692
    },
    {
      "source": "latimes.com",
      "target": "bostonherald.com",
      "weight": 0.012743884778430185,
      "tone_diff": 1.2370393381425375
    },
    {
      "source": "latimes.com",
      "target": "chicagotribune.com",
      "weight": 0.011903304024100517,
      "tone_diff": 1.293108422680168
    },
    {
      "source": "latimes.com",
      "target": "stltoday.com",
      "weight": 0.01944696171838644,
      "tone_diff": 1.2985632842449557
    },
    {
      "source": "latimes.com",
      "target": "seattlepi.com",
      "weight": 0.016801783046364104,
      "tone_diff": 1.2198305116912078
    },
    {
      "source": "latimes.com",
      "target": "nbclosangeles.com",
      "weight": 0.019275577208218597,
      "tone_diff": 1.288133574528027
    },
    {
      "source": "latimes.com",
      "target": "nbcphiladelphia.com",
      "weight": 0.012907010853622763,
      "tone_diff": 1.1539122176289092
    },
    {
      "source": "latimes.com",
      "target": "miamiherald.com",
      "weight": 0.014377035930343628,
      "tone_diff": 1.1510381383554624
    },
    {
      "source": "latimes.com",
      "target": "newsmax.com",
      "weight": 0.010225346633693629,
      "tone_diff": 1.7123689259079107
    },
    {
      "source": "latimes.com",
      "target": "nbcwashington.com",
      "weight": 0.021632430467187783,
      "tone_diff": 0.6899302040504053
    },
    {
      "source": "latimes.com",
      "target": "nbcnewyork.com",
      "weight": 0.016763121133506285,
      "tone_diff": 0.9329906367155584
    },
    {
      "source": "latimes.com",
      "target": "theonion.com",
      "weight": 0.015822784810126583,
      "tone_diff": 3.7871155934051
    },
    {
      "source": "latimes.com",
      "target": "abc7news.com",
      "weight": 0.011334013374135782,
      "tone_diff": 2.3399626471063404
    },
    {
      "source": "nbcnews.com",
      "target": "nydailynews.com",
      "weight": 0.015951557093425606,
      "tone_diff": 1.760076823677488
    },
    {
      "source": "nbcnews.com",
      "target": "seattletimes.com",
      "weight": 0.010424372856278162,
      "tone_diff": 2.088756679001097
    },
    {
      "source": "nbcnews.com",
      "target": "huffingtonpost.com",
      "weight": 0.021292285003226104,
      "tone_diff": 2.2999739530308294
    },
    {
      "source": "nbcnews.com",
      "target": "usatoday.com",
      "weight": 0.018804361141737107,
      "tone_diff": 2.412569652971813
    },
    {
      "source": "nbcnews.com",
      "target": "villagevoice.com",
      "weight": 0.021377672209026127,
      "tone_diff": 2.1133798319013706
    },
    {
      "source": "nbcnews.com",
      "target": "newsday.com",
      "weight": 0.020491127836070978,
      "tone_diff": 1.8643346383344452
    },
    {
      "source": "nbcnews.com",
      "target": "laweekly.com",
      "weight": 0.010554089709762533,
      "tone_diff": 4.256433605891349
    },
    {
      "source": "nbcnews.com",
      "target": "nbcchicago.com",
      "weight": 0.02440792653455776,
      "tone_diff": 1.4417622448075422
    },
    {
      "source": "nbcnews.com",
      "target": "denverpost.com",
      "weight": 0.018104696875646597,
      "tone_diff": 1.8203944149128788
    },
    {
      "source": "nbcnews.com",
      "target": "breitbart.com",
      "weight": 0.012200239808153478,
      "tone_diff": 2.462140584907344
    },
    {
      "source": "nbcnews.com",
      "target": "observer.com",
      "weight": 0.02110490378646803,
      "tone_diff": 3.1303968180715604
    },
    {
      "source": "nbcnews.com",
      "target": "nbcsandiego.com",
      "weight": 0.023207301173402868,
      "tone_diff": 1.5767302601896027
    },
    {
      "source": "nbcnews.com",
      "target": "twincities.com",
      "weight": 0.018693982074263763,
      "tone_diff": 1.5606396464583683
    },
    {
      "source": "nbcnews.com",
      "target": "mercurynews.com",
      "weight": 0.01881720430107527,
      "tone_diff": 1.8952037469296785
    },
    {
      "source": "nbcnews.com",
      "target": "bostonherald.com",
      "weight": 0.018457568656362725,
      "tone_diff": 1.6134826229662733
    },
    {
      "source": "nbcnews.com",
      "target": "chicagotribune.com",
      "weight": 0.013826688116874647,
      "tone_diff": 1.913560242636128
    },
    {
      "source": "nbcnews.com",
      "target": "nytimes.com",
      "weight": 0.010456304160138138,
      "tone_diff": 2.237198757670089
    },
    {
      "source": "nbcnews.com",
      "target": "gothamist.com",
      "weight": 0.025196850393700787,
      "tone_diff": 3.2770770075799107
    },
    {
      "source": "nbcnews.com",
      "target": "phillyvoice.com",
      "weight": 0.014726840855106888,
      "tone_diff": 2.335410451692019
    },
    {
      "source": "nbcnews.com",
      "target": "stltoday.com",
      "weight": 0.015029779749770156,
      "tone_diff": 1.7367893014872424
    },
    {
      "source": "nbcnews.com",
      "target": "seattlepi.com",
      "weight": 0.013670569156578516,
      "tone_diff": 1.7505655458515523
    },
    {
      "source": "nbcnews.com",
      "target": "nbclosangeles.com",
      "weight": 0.02584198263079856,
      "tone_diff": 1.5193610038861944
    },
    {
      "source": "nbcnews.com",
      "target": "newsweek.com",
      "weight": 0.01617662556644536,
      "tone_diff": 2.2833020909279935
    },
    {
      "source": "nbcnews.com",
      "target": "nbcphiladelphia.com",
      "weight": 0.01994719859196245,
      "tone_diff": 1.52893273440061
    },
    {
      "source": "nbcnews.com",
      "target": "politico.com",
      "weight": 0.020025301613749266,
      "tone_diff": 2.106729778604225
    },
    {
      "source": "nbcnews.com",
      "target": "miamiherald.com",
      "weight": 0.010330503882969118,
      "tone_diff": 1.774869784906187
    },
    {
      "source": "nbcnews.com",
      "target": "newsmax.com",
      "weight": 0.021645502792519936,
      "tone_diff": 1.8824943933908975
    },
    {
      "source": "nbcnews.com",
      "target": "miaminewtimes.com",
      "weight": 0.012084592145015106,
      "tone_diff": 3.830670844175125
    },
    {
      "source": "nbcnews.com",
      "target": "nbcwashington.com",
      "weight": 0.029630976186147972,
      "tone_diff": 1.6427656556605954
    },
    {
      "source": "nbcnews.com",
      "target": "nbcnewyork.com",
      "weight": 0.025344242666134505,
      "tone_diff": 1.7494845050342904
    },
    {
      "source": "nbcnews.com",
      "target": "theonion.com",
      "weight": 0.02531645569620253,
      "tone_diff": 3.2019372971087106
    },
    {
      "source": "nbcnews.com",
      "target": "abc7news.com",
      "weight": 0.02289470701575428,
      "tone_diff": 2.278137234972567
    },
    {
      "source": "newsday.com",
      "target": "nydailynews.com",
      "weight": 0.025874855793001153,
      "tone_diff": 1.0277007962725957
    },
    {
      "source": "newsday.com",
      "target": "seattletimes.com",
      "weight": 0.028951271768389825,
      "tone_diff": 1.0568012413597108
    },
    {
      "source": "newsday.com",
      "target": "nbcchicago.com",
      "weight": 0.017158047365877234,
      "tone_diff": 0.7556139457802397
    },
    {
      "source": "newsday.com",
      "target": "nbcsandiego.com",
      "weight": 0.01694915254237288,
      "tone_diff": 1.1085277267245852
    },
    {
      "source": "newsday.com",
      "target": "twincities.com",
      "weight": 0.011523687580025609,
      "tone_diff": 1.1127226304860347
    },
    {
      "source": "newsday.com",
      "target": "bostonherald.com",
      "weight": 0.03098390375212877,
      "tone_diff": 0.6870942778905791
    },
    {
      "source": "newsday.com",
      "target": "chicagotribune.com",
      "weight": 0.01972202384222381,
      "tone_diff": 1.0023264706903832
    },
    {
      "source": "newsday.com",
      "target": "stltoday.com",
      "weight": 0.040213151678294784,
      "tone_diff": 0.8224823534639839
    },
    {
      "source": "newsday.com",
      "target": "seattlepi.com",
      "weight": 0.03153326374773389,
      "tone_diff": 0.8920254206301582
    },
    {
      "source": "newsday.com",
      "target": "nbclosangeles.com",
      "weight": 0.013132810845159923,
      "tone_diff": 1.014184481444928
    },
    {
      "source": "newsday.com",
      "target": "nbcphiladelphia.com",
      "weight": 0.014373716632443531,
      "tone_diff": 0.7503694788689532
    },
    {
      "source": "newsday.com",
      "target": "miamiherald.com",
      "weight": 0.025710047794319617,
      "tone_diff": 0.9036746445864692
    },
    {
      "source": "newsday.com",
      "target": "newsmax.com",
      "weight": 0.01752458385980333,
      "tone_diff": 0.9309108001375788
    },
    {
      "source": "newsday.com",
      "target": "nbcwashington.com",
      "weight": 0.013815669878203964,
      "tone_diff": 0.7918383728185748
    },
    {
      "source": "newsday.com",
      "target": "nbcnewyork.com",
      "weight": 0.015366194372380763,
      "tone_diff": 0.9906807232611262
    },
    {
      "source": "newsmax.com",
      "target": "nydailynews.com",
      "weight": 0.02695267998555114,
      "tone_diff": 1.1792604852111208
    },
    {
      "source": "newsmax.com",
      "target": "seattletimes.com",
      "weight": 0.031092833921476007,
      "tone_diff": 1.0167696418521195
    },
    {
      "source": "newsmax.com",
      "target": "huffingtonpost.com",
      "weight": 0.013733984699050603,
      "tone_diff": 2.0993459087642012
    },
    {
      "source": "newsmax.com",
      "target": "nbcchicago.com",
      "weight": 0.02247462542290962,
      "tone_diff": 0.8613775808763381
    },
    {
      "source": "newsmax.com",
      "target": "denverpost.com",
      "weight": 0.014069935857645354,
      "tone_diff": 1.3303063856911088
    },
    {
      "source": "newsmax.com",
      "target": "observer.com",
      "weight": 0.0111731843575419,
      "tone_diff": 4.163150708789807
    },
    {
      "source": "newsmax.com",
      "target": "nbcsandiego.com",
      "weight": 0.026336375488917863,
      "tone_diff": 0.8754566182320002
    },
    {
      "source": "newsmax.com",
      "target": "twincities.com",
      "weight": 0.01357234314980794,
      "tone_diff": 1.330305584573952
    },
    {
      "source": "newsmax.com",
      "target": "mercurynews.com",
      "weight": 0.015348595213319459,
      "tone_diff": 1.760563442270731
    },
    {
      "source": "newsmax.com",
      "target": "bostonherald.com",
      "weight": 0.02050626580343994,
      "tone_diff": 0.9964575033412589
    },
    {
      "source": "newsmax.com",
      "target": "chicagotribune.com",
      "weight": 0.014004279085276057,
      "tone_diff": 1.309023740111986
    },
    {
      "source": "newsmax.com",
      "target": "nytimes.com",
      "weight": 0.01064214065408875,
      "tone_diff": 2.021997421664927
    },
    {
      "source": "newsmax.com",
      "target": "stltoday.com",
      "weight": 0.03453833115674234,
      "tone_diff": 1.0809702858856636
    },
    {
      "source": "newsmax.com",
      "target": "seattlepi.com",
      "weight": 0.03339909416766234,
      "tone_diff": 1.0267321009883736
    },
    {
      "source": "newsmax.com",
      "target": "nbclosangeles.com",
      "weight": 0.019911035797500528,
      "tone_diff": 0.9214132213901043
    },
    {
      "source": "newsmax.com",
      "target": "nbcphiladelphia.com",
      "weight": 0.021120563215019067,
      "tone_diff": 0.9917289031819099
    },
    {
      "source": "newsmax.com",
      "target": "politico.com",
      "weight": 0.011262303681076244,
      "tone_diff": 2.2257420451334986
    },
    {
      "source": "newsmax.com",
      "target": "miamiherald.com",
      "weight": 0.025591152852260414,
      "tone_diff": 1.0075661621044636
    },
    {
      "source": "newsmax.com",
      "target": "nbcwashington.com",
      "weight": 0.02926740592619524,
      "tone_diff": 0.9005078030229643
    },
    {
      "source": "newsmax.com",
      "target": "nbcnewyork.com",
      "weight": 0.02434643783675913,
      "tone_diff": 1.3776932366555596
    },
    {
      "source": "newsmax.com",
      "target": "abc7news.com",
      "weight": 0.01292077524651479,
      "tone_diff": 2.1028156525783164
    },
    {
      "source": "nytimes.com",
      "target": "seattletimes.com",
      "weight": 0.015172832795062834,
      "tone_diff": 1.1890026280663863
    },
    {
      "source": "nytimes.com",
      "target": "huffingtonpost.com",
      "weight": 0.012028758410913448,
      "tone_diff": 2.5107566937884407
    },
    {
      "source": "nytimes.com",
      "target": "villagevoice.com",
      "weight": 0.014251781472684086,
      "tone_diff": 2.8473774817561854
    },
    {
      "source": "nytimes.com",
      "target": "observer.com",
      "weight": 0.013966480446927373,
      "tone_diff": 3.1749991558174764
    },
    {
      "source": "nytimes.com",
      "target": "gothamist.com",
      "weight": 0.02204724409448819,
      "tone_diff": 2.932519516899833
    },
    {
      "source": "nytimes.com",
      "target": "seattlepi.com",
      "weight": 0.012119080356857354,
      "tone_diff": 1.3068023723526014
    },
    {
      "source": "nytimes.com",
      "target": "miamiherald.com",
      "weight": 0.011287692258497746,
      "tone_diff": 1.4204346823050564
    },
    {
      "source": "nytimes.com",
      "target": "nbcwashington.com",
      "weight": 0.01054353753862934,
      "tone_diff": 1.8355457449347954
    },
    {
      "source": "nytimes.com",
      "target": "nbcnewyork.com",
      "weight": 0.011374975054879265,
      "tone_diff": 2.2207290925752674
    },
    {
      "source": "nytimes.com",
      "target": "theonion.com",
      "weight": 0.022151898734177215,
      "tone_diff": 3.3722236493585243
    },
    {
      "source": "abc7news.com",
      "target": "bostonherald.com",
      "weight": 0.0206845744077978,
      "tone_diff": 1.4847579485537983
    },
    {
      "source": "abc7news.com",
      "target": "nydailynews.com",
      "weight": 0.01722770032868639,
      "tone_diff": 1.5781579938243242
    },
    {
      "source": "abc7news.com",
      "target": "seattletimes.com",
      "weight": 0.017454380596169102,
      "tone_diff": 2.0384201657480543
    },
    {
      "source": "abc7news.com",
      "target": "usatoday.com",
      "weight": 0.010257282103592882,
      "tone_diff": 2.0890077713643582
    },
    {
      "source": "abc7news.com",
      "target": "stltoday.com",
      "weight": 0.032641958517511054,
      "tone_diff": 1.4963686355649897
    },
    {
      "source": "abc7news.com",
      "target": "seattlepi.com",
      "weight": 0.01620763912501417,
      "tone_diff": 1.8203485400433512
    },
    {
      "source": "abc7news.com",
      "target": "newsweek.com",
      "weight": 0.010540632437946278,
      "tone_diff": 2.4382058536523146
    },
    {
      "source": "abc7news.com",
      "target": "miamiherald.com",
      "weight": 0.015697608523178058,
      "tone_diff": 1.5963861724752617
    },
    {
      "source": "abc7news.com",
      "target": "chicagotribune.com",
      "weight": 0.012580754845290717,
      "tone_diff": 2.0919633129422124
    },
    {
      "source": "abc7news.com",
      "target": "nbcsandiego.com",
      "weight": 0.010951760104302478,
      "tone_diff": 1.5082025612991172
    },
    {
      "source": "abc7news.com",
      "target": "nbcnewyork.com",
      "weight": 0.01197365795250449,
      "tone_diff": 1.3201001505574153
    },
    {
      "source": "abc7news.com",
      "target": "twincities.com",
      "weight": 0.010499359795134442,
      "tone_diff": 1.3792932579690667
    },
    {
      "source": "laweekly.com",
      "target": "huffingtonpost.com",
      "weight": 0.010554089709762533,
      "tone_diff": 3.4377942666522765
    },
    {
      "source": "laweekly.com",
      "target": "newsweek.com",
      "weight": 0.010554089709762533,
      "tone_diff": 3.3992014300193962
    },
    {
      "source": "newsweek.com",
      "target": "gothamist.com",
      "weight": 0.012598425196850394,
      "tone_diff": 2.3174524731303228
    },
    {
      "source": "newsweek.com",
      "target": "huffingtonpost.com",
      "weight": 0.010600055304636372,
      "tone_diff": 2.31110563694856
    },
    {
      "source": "newsweek.com",
      "target": "observer.com",
      "weight": 0.010242085661080074,
      "tone_diff": 2.9188166836468192
    },
    {
      "source": "newsweek.com",
      "target": "theonion.com",
      "weight": 0.012658227848101266,
      "tone_diff": 3.9866529505409045
    },
    {
      "source": "observer.com",
      "target": "nydailynews.com",
      "weight": 0.019242706393544383,
      "tone_diff": 2.9399216296438495
    },
    {
      "source": "observer.com",
      "target": "seattletimes.com",
      "weight": 0.011483550589695841,
      "tone_diff": 3.4966191300559393
    },
    {
      "source": "observer.com",
      "target": "huffingtonpost.com",
      "weight": 0.010552451893234015,
      "tone_diff": 3.0044621438422676
    },
    {
      "source": "observer.com",
      "target": "stltoday.com",
      "weight": 0.010242085661080074,
      "tone_diff": 2.7956830478292574
    },
    {
      "source": "politico.com",
      "target": "nydailynews.com",
      "weight": 0.0116634268258817,
      "tone_diff": 2.039035106355658
    },
    {
      "source": "politico.com",
      "target": "seattletimes.com",
      "weight": 0.011509148693264217,
      "tone_diff": 2.355262433282568
    },
    {
      "source": "politico.com",
      "target": "huffingtonpost.com",
      "weight": 0.012996589547423726,
      "tone_diff": 2.341593365614677
    },
    {
      "source": "politico.com",
      "target": "villagevoice.com",
      "weight": 0.010688836104513063,
      "tone_diff": 2.384552532475944
    },
    {
      "source": "politico.com",
      "target": "stltoday.com",
      "weight": 0.013607331296861983,
      "tone_diff": 1.961639757294163
    },
    {
      "source": "politico.com",
      "target": "theonion.com",
      "weight": 0.015822784810126583,
      "tone_diff": 2.4780380656191427
    },
    {
      "source": "stltoday.com",
      "target": "bostonherald.com",
      "weight": 0.10529503146475684,
      "tone_diff": 0.579150835959982
    },
    {
      "source": "stltoday.com",
      "target": "phillyvoice.com",
      "weight": 0.01140142517814727,
      "tone_diff": 2.6020079028447496
    },
    {
      "source": "stltoday.com",
      "target": "nydailynews.com",
      "weight": 0.09385813148788927,
      "tone_diff": 0.5400566287244751
    },
    {
      "source": "stltoday.com",
      "target": "seattletimes.com",
      "weight": 0.046768197625614585,
      "tone_diff": 0.7823856872945862
    },
    {
      "source": "stltoday.com",
      "target": "huffingtonpost.com",
      "weight": 0.012535717577656928,
      "tone_diff": 2.290993534113907
    },
    {
      "source": "stltoday.com",
      "target": "usatoday.com",
      "weight": 0.016752419453632244,
      "tone_diff": 1.904436412930592
    },
    {
      "source": "stltoday.com",
      "target": "seattlepi.com",
      "weight": 0.07040129735266085,
      "tone_diff": 0.5371275402539963
    },
    {
      "source": "stltoday.com",
      "target": "nbclosangeles.com",
      "weight": 0.04871849184494811,
      "tone_diff": 0.8021471539831833
    },
    {
      "source": "stltoday.com",
      "target": "nbcchicago.com",
      "weight": 0.053165780570323826,
      "tone_diff": 0.6880334465738007
    },
    {
      "source": "stltoday.com",
      "target": "denverpost.com",
      "weight": 0.041795985930064145,
      "tone_diff": 0.9307850941169605
    },
    {
      "source": "stltoday.com",
      "target": "nbcphiladelphia.com",
      "weight": 0.058961572308594896,
      "tone_diff": 0.610366027756689
    },
    {
      "source": "stltoday.com",
      "target": "breitbart.com",
      "weight": 0.014178657074340528,
      "tone_diff": 1.712104357472092
    },
    {
      "source": "stltoday.com",
      "target": "miamiherald.com",
      "weight": 0.060252361727358726,
      "tone_diff": 0.7374241507687607
    },
    {
      "source": "stltoday.com",
      "target": "chicagotribune.com",
      "weight": 0.031175268489934346,
      "tone_diff": 0.9285493992704483
    },
    {
      "source": "stltoday.com",
      "target": "nbcwashington.com",
      "weight": 0.06471550627158698,
      "tone_diff": 0.8766367166368074
    },
    {
      "source": "stltoday.com",
      "target": "nbcsandiego.com",
      "weight": 0.061016949152542375,
      "tone_diff": 0.5946051632921577
    },
    {
      "source": "stltoday.com",
      "target": "nbcnewyork.com",
      "weight": 0.05428058271802035,
      "tone_diff": 0.8573858176892672
    },
    {
      "source": "stltoday.com",
      "target": "theonion.com",
      "weight": 0.012658227848101266,
      "tone_diff": 2.310213785847832
    },
    {
      "source": "stltoday.com",
      "target": "twincities.com",
      "weight": 0.06837387964148528,
      "tone_diff": 0.7547163803836939
    },
    {
      "source": "stltoday.com",
      "target": "mercurynews.com",
      "weight": 0.05194242108914325,
      "tone_diff": 0.9041722248251025
    },
    {
      "source": "theonion.com",
      "target": "bostonherald.com",
      "weight": 0.012658227848101266,
      "tone_diff": 1.2845037870174152
    },
    {
      "source": "theonion.com",
      "target": "seattletimes.com",
      "weight": 0.012658227848101266,
      "tone_diff": 3.361581552936916
    },
    {
      "source": "usatoday.com",
      "target": "bostonherald.com",
      "weight": 0.01114786230552493,
      "tone_diff": 1.7048101135807134
    },
    {
      "source": "usatoday.com",
      "target": "gothamist.com",
      "weight": 0.011023622047244094,
      "tone_diff": 3.793137845918504
    },
    {
      "source": "usatoday.com",
      "target": "nydailynews.com",
      "weight": 0.014792355751561926,
      "tone_diff": 2.0054133142254233
    },
    {
      "source": "usatoday.com",
      "target": "seattletimes.com",
      "weight": 0.013352933970354036,
      "tone_diff": 2.224282689198292
    },
    {
      "source": "usatoday.com",
      "target": "seattlepi.com",
      "weight": 0.01304667401690555,
      "tone_diff": 1.9205947360584164
    },
    {
      "source": "usatoday.com",
      "target": "miamiherald.com",
      "weight": 0.012066642165870391,
      "tone_diff": 1.8952345998652318
    },
    {
      "source": "usatoday.com",
      "target": "nbcwashington.com",
      "weight": 0.011270678058534812,
      "tone_diff": 2.1027222409000252
    },
    {
      "source": "usatoday.com",
      "target": "nbcnewyork.com",
      "weight": 0.013769706645380164,
      "tone_diff": 2.154220562927238
    },
    {
      "source": "westword.com",
      "target": "denverpost.com",
      "weight": 0.010946555054732776,
      "tone_diff": 4.128856510018489
    },
    {
      "source": "gothamist.com",
      "target": "nydailynews.com",
      "weight": 0.015748031496062992,
      "tone_diff": 3.0129199067721424
    },
    {
      "source": "seattlepi.com",
      "target": "bostonherald.com",
      "weight": 0.05484609916006214,
      "tone_diff": 0.8073406145003446
    },
    {
      "source": "seattlepi.com",
      "target": "nydailynews.com",
      "weight": 0.04875432525951557,
      "tone_diff": 0.6984502704191301
    },
    {
      "source": "seattlepi.com",
      "target": "seattletimes.com",
      "weight": 0.0755651023514517,
      "tone_diff": 0.5617867582579358
    },
    {
      "source": "seattlepi.com",
      "target": "huffingtonpost.com",
      "weight": 0.010139183334869573,
      "tone_diff": 2.3464033642931073
    },
    {
      "source": "seattlepi.com",
      "target": "nbclosangeles.com",
      "weight": 0.04151662783308621,
      "tone_diff": 0.6924037606886023
    },
    {
      "source": "seattlepi.com",
      "target": "nbcchicago.com",
      "weight": 0.04229096181730305,
      "tone_diff": 0.7111980317986195
    },
    {
      "source": "seattlepi.com",
      "target": "denverpost.com",
      "weight": 0.021932547072211876,
      "tone_diff": 0.8418577770715683
    },
    {
      "source": "seattlepi.com",
      "target": "nbcphiladelphia.com",
      "weight": 0.04136110296274567,
      "tone_diff": 0.5740849117903165
    },
    {
      "source": "seattlepi.com",
      "target": "miamiherald.com",
      "weight": 0.06368692831842042,
      "tone_diff": 0.82485291815431
    },
    {
      "source": "seattlepi.com",
      "target": "chicagotribune.com",
      "weight": 0.024892386625505455,
      "tone_diff": 0.880329936221831
    },
    {
      "source": "seattlepi.com",
      "target": "nbcwashington.com",
      "weight": 0.04508271223413925,
      "tone_diff": 0.6821419776339847
    },
    {
      "source": "seattlepi.com",
      "target": "nbcsandiego.com",
      "weight": 0.051629726205997394,
      "tone_diff": 0.6722627549051353
    },
    {
      "source": "seattlepi.com",
      "target": "nbcnewyork.com",
      "weight": 0.041508680902015566,
      "tone_diff": 0.6977780086678232
    },
    {
      "source": "seattlepi.com",
      "target": "twincities.com",
      "weight": 0.03149807938540333,
      "tone_diff": 0.7574205960187349
    },
    {
      "source": "seattlepi.com",
      "target": "mercurynews.com",
      "weight": 0.027315296566077004,
      "tone_diff": 0.7915424267289898
    },
    {
      "source": "denverpost.com",
      "target": "bostonherald.com",
      "weight": 0.02451893234016139,
      "tone_diff": 0.755678781982113
    },
    {
      "source": "denverpost.com",
      "target": "nydailynews.com",
      "weight": 0.02669149596523898,
      "tone_diff": 1.0430226715261717
    },
    {
      "source": "denverpost.com",
      "target": "seattletimes.com",
      "weight": 0.030726256983240222,
      "tone_diff": 0.9372756846604242
    },
    {
      "source": "denverpost.com",
      "target": "mercurynews.com",
      "weight": 0.01334574798261949,
      "tone_diff": 0.7062843254549533
    },
    {
      "source": "denverpost.com",
      "target": "miamiherald.com",
      "weight": 0.017277053589902752,
      "tone_diff": 1.3619390718328253
    },
    {
      "source": "denverpost.com",
      "target": "twincities.com",
      "weight": 0.015108834827144686,
      "tone_diff": 0.5558697616808226
    },
    {
      "source": "denverpost.com",
      "target": "chicagotribune.com",
      "weight": 0.016035588661286987,
      "tone_diff": 0.9690994189990897
    },
    {
      "source": "nbcchicago.com",
      "target": "bostonherald.com",
      "weight": 0.039149347510874816,
      "tone_diff": 0.8258569953416339
    },
    {
      "source": "nbcchicago.com",
      "target": "nydailynews.com",
      "weight": 0.04180763653939101,
      "tone_diff": 0.6369281002081615
    },
    {
      "source": "nbcchicago.com",
      "target": "seattletimes.com",
      "weight": 0.030207829869502174,
      "tone_diff": 0.7444108216499074
    },
    {
      "source": "nbcchicago.com",
      "target": "nbclosangeles.com",
      "weight": 0.049782503624939585,
      "tone_diff": 0.11334451715911152
    },
    {
      "source": "nbcchicago.com",
      "target": "nbcphiladelphia.com",
      "weight": 0.06277500733352889,
      "tone_diff": 0.10442658238129215
    },
    {
      "source": "nbcchicago.com",
      "target": "miamiherald.com",
      "weight": 0.038424359594006766,
      "tone_diff": 0.8393287709996978
    },
    {
      "source": "nbcchicago.com",
      "target": "chicagotribune.com",
      "weight": 0.029966167230546157,
      "tone_diff": 1.5510265710755278
    },
    {
      "source": "nbcchicago.com",
      "target": "nbcwashington.com",
      "weight": 0.06863218946350894,
      "tone_diff": 0.14209074403305433
    },
    {
      "source": "nbcchicago.com",
      "target": "nbcsandiego.com",
      "weight": 0.07822685788787484,
      "tone_diff": 0.10368472362804784
    },
    {
      "source": "nbcchicago.com",
      "target": "nbcnewyork.com",
      "weight": 0.051715804736587725,
      "tone_diff": 0.1168906237169017
    },
    {
      "source": "nbcnewyork.com",
      "target": "bostonherald.com",
      "weight": 0.03751746158451407,
      "tone_diff": 0.8981701828523139
    },
    {
      "source": "nbcnewyork.com",
      "target": "nydailynews.com",
      "weight": 0.040510876072640194,
      "tone_diff": 1.093811084873525
    },
    {
      "source": "nbcnewyork.com",
      "target": "seattletimes.com",
      "weight": 0.038914388345639594,
      "tone_diff": 1.0063565358081006
    },
    {
      "source": "nbcnewyork.com",
      "target": "nbclosangeles.com",
      "weight": 0.038339334886676554,
      "tone_diff": 0.14131423035041396
    },
    {
      "source": "nbcnewyork.com",
      "target": "nbcphiladelphia.com",
      "weight": 0.061014960398943975,
      "tone_diff": 0.11493035564192014
    },
    {
      "source": "nbcnewyork.com",
      "target": "miamiherald.com",
      "weight": 0.037317900618638995,
      "tone_diff": 0.928421362466799
    },
    {
      "source": "nbcnewyork.com",
      "target": "nbcsandiego.com",
      "weight": 0.059191655801825296,
      "tone_diff": 0.12786872567340904
    },
    {
      "source": "nbcnewyork.com",
      "target": "nbcwashington.com",
      "weight": 0.05587707044502095,
      "tone_diff": 0.11781404191681055
    },
    {
      "source": "nbcnewyork.com",
      "target": "chicagotribune.com",
      "weight": 0.024545998802634205,
      "tone_diff": 0.9799068741951045
    },
    {
      "source": "twincities.com",
      "target": "bostonherald.com",
      "weight": 0.04225352112676056,
      "tone_diff": 0.7264596643751945
    },
    {
      "source": "twincities.com",
      "target": "nydailynews.com",
      "weight": 0.03482714468629962,
      "tone_diff": 0.9277509837028903
    },
    {
      "source": "twincities.com",
      "target": "seattletimes.com",
      "weight": 0.03713188220230474,
      "tone_diff": 1.0761034143867731
    },
    {
      "source": "twincities.com",
      "target": "miamiherald.com",
      "weight": 0.023303457106274007,
      "tone_diff": 1.0359187540279007
    },
    {
      "source": "twincities.com",
      "target": "chicagotribune.com",
      "weight": 0.020998719590268885,
      "tone_diff": 1.3354750923956349
    },
    {
      "source": "twincities.com",
      "target": "mercurynews.com",
      "weight": 0.012548015364916773,
      "tone_diff": 0.9212343481209514
    },
    {
      "source": "mercurynews.com",
      "target": "bostonherald.com",
      "weight": 0.02480055497745404,
      "tone_diff": 0.8838128286928091
    },
    {
      "source": "mercurynews.com",
      "target": "nydailynews.com",
      "weight": 0.030003468609087754,
      "tone_diff": 1.2692933267026434
    },
    {
      "source": "mercurynews.com",
      "target": "seattletimes.com",
      "weight": 0.03043704474505723,
      "tone_diff": 1.2215342451333626
    },
    {
      "source": "mercurynews.com",
      "target": "miamiherald.com",
      "weight": 0.020898369753728756,
      "tone_diff": 1.1418435703329775
    },
    {
      "source": "mercurynews.com",
      "target": "nbcsandiego.com",
      "weight": 0.010951760104302478,
      "tone_diff": 0.5056698703396277
    },
    {
      "source": "mercurynews.com",
      "target": "chicagotribune.com",
      "weight": 0.02592785293097468,
      "tone_diff": 0.8220185542481151
    },
    {
      "source": "miamiherald.com",
      "target": "bostonherald.com",
      "weight": 0.053871876563363966,
      "tone_diff": 0.5947570502593814
    },
    {
      "source": "miamiherald.com",
      "target": "nydailynews.com",
      "weight": 0.05546712802768166,
      "tone_diff": 0.7514551356266923
    },
    {
      "source": "miamiherald.com",
      "target": "seattletimes.com",
      "weight": 0.049063873336945396,
      "tone_diff": 0.866897448175016
    },
    {
      "source": "miamiherald.com",
      "target": "nbcwashington.com",
      "weight": 0.04490092710416288,
      "tone_diff": 0.8965617333956025
    },
    {
      "source": "miamiherald.com",
      "target": "nbclosangeles.com",
      "weight": 0.039822071595001056,
      "tone_diff": 0.8979298680795953
    },
    {
      "source": "miamiherald.com",
      "target": "miaminewtimes.com",
      "weight": 0.01661631419939577,
      "tone_diff": 3.16243753077526
    },
    {
      "source": "miamiherald.com",
      "target": "nbcphiladelphia.com",
      "weight": 0.04458785567615137,
      "tone_diff": 0.8481765310212898
    },
    {
      "source": "miamiherald.com",
      "target": "nbcsandiego.com",
      "weight": 0.046153846153846156,
      "tone_diff": 0.8185631396461662
    },
    {
      "source": "miamiherald.com",
      "target": "chicagotribune.com",
      "weight": 0.021740075655463282,
      "tone_diff": 1.0531931911674002
    },
    {
      "source": "nbcsandiego.com",
      "target": "bostonherald.com",
      "weight": 0.03624511082138201,
      "tone_diff": 0.7069939690346362
    },
    {
      "source": "nbcsandiego.com",
      "target": "nydailynews.com",
      "weight": 0.043546284224250324,
      "tone_diff": 0.59667138015952
    },
    {
      "source": "nbcsandiego.com",
      "target": "seattletimes.com",
      "weight": 0.03650586701434159,
      "tone_diff": 0.8598572061579457
    },
    {
      "source": "nbcsandiego.com",
      "target": "nbclosangeles.com",
      "weight": 0.06857887874837028,
      "tone_diff": 0.14909743128668404
    },
    {
      "source": "nbcsandiego.com",
      "target": "nbcphiladelphia.com",
      "weight": 0.059548254620123205,
      "tone_diff": 0.11923444807477017
    },
    {
      "source": "nbcsandiego.com",
      "target": "nbcwashington.com",
      "weight": 0.0727509778357236,
      "tone_diff": 0.12811872094459392
    },
    {
      "source": "nbcsandiego.com",
      "target": "chicagotribune.com",
      "weight": 0.023207301173402868,
      "tone_diff": 1.112753796052725
    },
    {
      "source": "nydailynews.com",
      "target": "bostonherald.com",
      "weight": 0.07596303220200637,
      "tone_diff": 0.5662928652984148
    },
    {
      "source": "nydailynews.com",
      "target": "phillyvoice.com",
      "weight": 0.013776722090261283,
      "tone_diff": 1.7960438770241558
    },
    {
      "source": "nydailynews.com",
      "target": "seattletimes.com",
      "weight": 0.03503460207612457,
      "tone_diff": 1.0500156580473592
    },
    {
      "source": "nydailynews.com",
      "target": "huffingtonpost.com",
      "weight": 0.014563554244630841,
      "tone_diff": 2.1887728298101536
    },
    {
      "source": "nydailynews.com",
      "target": "villagevoice.com",
      "weight": 0.013064133016627079,
      "tone_diff": 2.7547553359928325
    },
    {
      "source": "nydailynews.com",
      "target": "nbclosangeles.com",
      "weight": 0.0347384028807456,
      "tone_diff": 0.6358021207043244
    },
    {
      "source": "nydailynews.com",
      "target": "nbcphiladelphia.com",
      "weight": 0.031387503666764446,
      "tone_diff": 0.7369100966235341
    },
    {
      "source": "nydailynews.com",
      "target": "nbcwashington.com",
      "weight": 0.04399200145428104,
      "tone_diff": 0.7447026016609254
    },
    {
      "source": "nydailynews.com",
      "target": "chicagotribune.com",
      "weight": 0.020826992477933823,
      "tone_diff": 1.1266256351141513
    },
    {
      "source": "bostonherald.com",
      "target": "seattletimes.com",
      "weight": 0.03815266331393665,
      "tone_diff": 0.9416700264170351
    },
    {
      "source": "bostonherald.com",
      "target": "nbclosangeles.com",
      "weight": 0.034102944291463676,
      "tone_diff": 0.7063685820851425
    },
    {
      "source": "bostonherald.com",
      "target": "nbcphiladelphia.com",
      "weight": 0.041654444118509826,
      "tone_diff": 0.6972281536204373
    },
    {
      "source": "bostonherald.com",
      "target": "nbcwashington.com",
      "weight": 0.04217415015451736,
      "tone_diff": 0.7613448462692565
    },
    {
      "source": "bostonherald.com",
      "target": "chicagotribune.com",
      "weight": 0.020879959977882515,
      "tone_diff": 0.9762498025915576
    },
    {
      "source": "seattletimes.com",
      "target": "huffingtonpost.com",
      "weight": 0.012766153562540326,
      "tone_diff": 2.546956136844511
    },
    {
      "source": "seattletimes.com",
      "target": "nbclosangeles.com",
      "weight": 0.03219656852361788,
      "tone_diff": 0.9176547665436607
    },
    {
      "source": "seattletimes.com",
      "target": "nbcphiladelphia.com",
      "weight": 0.03490759753593429,
      "tone_diff": 0.9114675169514375
    },
    {
      "source": "seattletimes.com",
      "target": "nbcwashington.com",
      "weight": 0.04162879476458826,
      "tone_diff": 0.9716378317805696
    },
    {
      "source": "seattletimes.com",
      "target": "chicagotribune.com",
      "weight": 0.025414148441236576,
      "tone_diff": 1.0522862045457093
    },
    {
      "source": "nbclosangeles.com",
      "target": "nbcwashington.com",
      "weight": 0.047871213725905526,
      "tone_diff": 0.17248774336845168
    },
    {
      "source": "nbclosangeles.com",
      "target": "chicagotribune.com",
      "weight": 0.0226646896843889,
      "tone_diff": 0.7789688500186375
    },
    {
      "source": "nbclosangeles.com",
      "target": "nbcphiladelphia.com",
      "weight": 0.05690818421824582,
      "tone_diff": 0.08933154801306646
    },
    {
      "source": "nbcwashington.com",
      "target": "nbcphiladelphia.com",
      "weight": 0.06570841889117043,
      "tone_diff": 0.1170180490943519
    },
    {
      "source": "nbcwashington.com",
      "target": "chicagotribune.com",
      "weight": 0.024359207416833305,
      "tone_diff": 0.7643300149149324
    },
    {
      "source": "chicagotribune.com",
      "target": "nbcphiladelphia.com",
      "weight": 0.0196538574361983,
      "tone_diff": 0.7796205922273581
    }
  ]
}